pomme/__init__.py
pomme/forward.py
pomme/haar.py
pomme/hydrodynamics.py
pomme/lines.py
pomme/loss.py
pomme/model.py
pomme/object.py
pomme/observation.py
pomme/plot.py
pomme/utils.py
pomme-0.2.1.dist-info/licenses/LICENSE
pomme-0.2.1.dist-info/METADATA
pomme-0.2.1.dist-info/WHEEL
pomme-0.2.1.dist-info/top_level.txt
pomme-0.2.1.dist-info/RECORD
