Metadata-Version: 2.4
Name: pomme
Version: 0.2.1
Summary: Probabilistic 3D Reconstruction of Spectral Line Observations.
Author-email: Frederik De Ceuster <frederik.deceuster@gmail.com>
License:                     GNU GENERAL PUBLIC LICENSE
Project-URL: Homepage, https://github.com/Magritte-code/pomme
Keywords: 3D Reconstruction,Astrophysics,Astronomy
Classifier: License :: OSI Approved :: GNU General Public License v3 (GPLv3)
Classifier: Programming Language :: Python
Classifier: Programming Language :: Python :: 3
Classifier: Topic :: Scientific/Engineering :: Physics
Classifier: Topic :: Scientific/Engineering :: Astronomy
Classifier: Topic :: Scientific/Engineering :: Visualization
Classifier: Topic :: Scientific/Engineering :: Image Processing
Requires-Python: >=3.7
License-File: LICENSE
Requires-Dist: matplotlib
Requires-Dist: astroquery
Requires-Dist: radio-beam
Requires-Dist: ipywidgets
Requires-Dist: astropy
Requires-Dist: torch>=2.0.0
Requires-Dist: numpy
Requires-Dist: numba
Requires-Dist: tqdm
Requires-Dist: h5py
Provides-Extra: dev
Requires-Dist: black; extra == "dev"
Requires-Dist: bumpver; extra == "dev"
Requires-Dist: pip-tools; extra == "dev"
Requires-Dist: pytest; extra == "dev"
Dynamic: license-file
